xre/__init__.py
xre-0.0.1.dist-info/METADATA
xre-0.0.1.dist-info/WHEEL
xre-0.0.1.dist-info/top_level.txt
xre-0.0.1.dist-info/RECORD
