Metadata-Version: 2.1
Name: xre
Version: 0.0.1
Summary: Build regex like legos.
Home-page: https://github.com/polyrand
Author: Ricardo Ander-Egg
Author-email: ricardo.anderegg@gmail.com
License: MIT
Platform: UNKNOWN
Classifier: Programming Language :: Python :: 3
Classifier: License :: OSI Approved :: MIT License
Classifier: Operating System :: OS Independent
Classifier: Development Status :: 2 - Pre-Alpha
Requires-Python: >=3.7
